envconfig/__init__.py
envconfig/__version__.py
envconfig/config.py
envconfig/param.py
py_envconfig-0.7.0.dist-info/METADATA
py_envconfig-0.7.0.dist-info/WHEEL
py_envconfig-0.7.0.dist-info/top_level.txt
py_envconfig-0.7.0.dist-info/RECORD
