Metadata-Version: 2.1
Name: py-envconfig
Version: 0.7.0
Summary: Managing environment config data
Home-page: UNKNOWN
Author: S. Williams-Wynn
Author-email: s.williamswynn.mail@gmail.com
License: UNKNOWN
Platform: UNKNOWN
Requires-Python: >=3.6
Requires-Dist: toolz
Requires-Dist: python-dotenv
